totalsegmentator/__init__.py
totalsegmentator/alignment.py
totalsegmentator/config.py
totalsegmentator/cropping.py
totalsegmentator/custom_trainers.py
totalsegmentator/dicom_io.py
totalsegmentator/dicom_utils.py
totalsegmentator/download_pretrained_weights.py
totalsegmentator/excel.py
totalsegmentator/libs.py
totalsegmentator/map_to_binary.py
totalsegmentator/map_to_total.py
totalsegmentator/nifti_ext_header.py
totalsegmentator/nnunet.py
totalsegmentator/postprocessing.py
totalsegmentator/preview.py
totalsegmentator/python_api.py
totalsegmentator/registration.py
totalsegmentator/resample_nnunet.py
totalsegmentator/resampling.py
totalsegmentator/serialization_utils.py
totalsegmentator/statistics.py
totalsegmentator/vtk_utils.py
totalsegmentator/bin/TotalSegmentator.py
totalsegmentator/bin/__init__.py
totalsegmentator/bin/crop_to_body.py
totalsegmentator/bin/totalseg_combine_masks.py
totalsegmentator/bin/totalseg_download_weights.py
totalsegmentator/bin/totalseg_evans_index.py
totalsegmentator/bin/totalseg_get_modality.py
totalsegmentator/bin/totalseg_get_phase.py
totalsegmentator/bin/totalseg_import_weights.py
totalsegmentator/bin/totalseg_set_license.py
totalsegmentator/bin/totalseg_setup_manually.py
totalsegmentator/resources/contrast_phase_classifiers_2024_07_19.pkl
totalsegmentator/resources/ct_brain_atlas_1mm.nii.gz
totalsegmentator/resources/modality_classifiers_2024_10_04.pkl
totalsegmentator/resources/modality_classifiers_2025_02_24.json.0
totalsegmentator/resources/modality_classifiers_2025_02_24.json.1
totalsegmentator/resources/modality_classifiers_2025_02_24.json.2
totalsegmentator/resources/modality_classifiers_2025_02_24.json.3
totalsegmentator/resources/modality_classifiers_2025_02_24.json.4
totalsegmentator/resources/modality_classifiers_normalized_2025_02_24.json.0
totalsegmentator/resources/modality_classifiers_normalized_2025_02_24.json.1
totalsegmentator/resources/modality_classifiers_normalized_2025_02_24.json.2
totalsegmentator-2.12.0.dist-info/licenses/LICENSE
totalsegmentator-2.12.0.dist-info/METADATA
totalsegmentator-2.12.0.dist-info/WHEEL
totalsegmentator-2.12.0.dist-info/entry_points.txt
totalsegmentator-2.12.0.dist-info/top_level.txt
totalsegmentator-2.12.0.dist-info/RECORD
