Metadata-Version: 2.4
Name: TotalSegmentator
Version: 2.12.0
Summary: Robust segmentation of 104 classes in CT images.
Home-page: https://github.com/wasserth/TotalSegmentator
Author: Jakob Wasserthal
Author-email: jakob.wasserthal@usb.ch
License: Apache 2.0
Classifier: Intended Audience :: Science/Research
Classifier: Programming Language :: Python
Classifier: Topic :: Scientific/Engineering
Classifier: Operating System :: Unix
Classifier: Operating System :: MacOS
Requires-Python: >=3.9
License-File: LICENSE
Requires-Dist: torch>=2.1.2
Requires-Dist: numpy
Requires-Dist: SimpleITK
Requires-Dist: nibabel>=2.3.0
Requires-Dist: tqdm>=4.45.0
Requires-Dist: xvfbwrapper
Requires-Dist: nnunetv2>=2.3.1
Requires-Dist: requests==2.27.1; python_version < "3.10"
Requires-Dist: requests; python_version >= "3.10"
Requires-Dist: dicom2nifti
Requires-Dist: pyarrow
Dynamic: author
Dynamic: author-email
Dynamic: classifier
Dynamic: description
Dynamic: home-page
Dynamic: license
Dynamic: license-file
Dynamic: requires-dist
Dynamic: requires-python
Dynamic: summary
